[
    {
        "type": "click",
        "element": {
            "index": "4",
            "text": "",
            "resource-id": "com.target.ui:id/menu_account",
            "class": "android.widget.FrameLayout",
            "package": "com.target.ui",
            "content-desc": "My Target",
            "checkable": "false",
            "checked": "false",
            "clickable": "true",
            "enabled": "true",
            "focusable": "true",
            "focused": "false",
            "scrollable": "false",
            "long-clickable": "false",
            "password": "false",
            "selected": "false",
            "visible-to-user": "true",
            "bounds": "[615,1070][768,1182]",
            "drawing-order": "5",
            "hint": "",
            "display-id": "0"
        }
    },
    {
        "type": "swipe",
        "element": {
            "index": "0",
            "text": "",
            "resource-id": "com.android.systemui:id/navigation_bar_frame",
            "class": "android.widget.FrameLayout",
            "package": "com.android.systemui",
            "content-desc": "",
            "checkable": "false",
            "checked": "false",
            "clickable": "false",
            "enabled": "true",
            "focusable": "false",
            "focused": "false",
            "scrollable": "false",
            "long-clickable": "false",
            "password": "false",
            "selected": "false",
            "visible-to-user": "true",
            "bounds": "[0,1184][768,1280]",
            "drawing-order": "0",
            "hint": "",
            "display-id": "0"
        }
    },
    {
        "type": "click",
        "element": {
            "index": "0",
            "text": "Help center",
            "resource-id": "com.target.ui:id/cell_name",
            "class": "android.widget.Button",
            "package": "com.target.ui",
            "content-desc": "",
            "checkable": "false",
            "checked": "false",
            "clickable": "true",
            "enabled": "true",
            "focusable": "true",
            "focused": "false",
            "scrollable": "false",
            "long-clickable": "false",
            "password": "false",
            "selected": "false",
            "visible-to-user": "true",
            "bounds": "[32,294][736,422]",
            "drawing-order": "2",
            "hint": "",
            "display-id": "0"
        }
    },
    {
        "type": "click",
        "element": {
            "index": "1",
            "text": "Contact Options",
            "resource-id": "com.target.ui:id/headLine",
            "class": "android.widget.TextView",
            "package": "com.target.ui",
            "content-desc": "Contact Options",
            "checkable": "false",
            "checked": "false",
            "clickable": "false",
            "enabled": "true",
            "focusable": "false",
            "focused": "false",
            "scrollable": "false",
            "long-clickable": "false",
            "password": "false",
            "selected": "false",
            "visible-to-user": "true",
            "bounds": "[24,203][668,245]",
            "drawing-order": "4",
            "hint": "",
            "display-id": "0"
        }
    },
    {
        "type": "click",
        "element": {
            "index": "1",
            "text": "Contact Us About Target Order Experience",
            "resource-id": "com.target.ui:id/headLine",
            "class": "android.widget.TextView",
            "package": "com.target.ui",
            "content-desc": "Contact Us About Target Order Experience",
            "checkable": "false",
            "checked": "false",
            "clickable": "false",
            "enabled": "true",
            "focusable": "false",
            "focused": "false",
            "scrollable": "false",
            "long-clickable": "false",
            "password": "false",
            "selected": "false",
            "visible-to-user": "true",
            "bounds": "[24,183][668,266]",
            "drawing-order": "4",
            "hint": "",
            "display-id": "0"
        }
    },
    {
        "type": "click",
        "element": {
            "index": "0",
            "text": "Contact",
            "resource-id": "com.target.ui:id/menu_contact",
            "class": "android.widget.Button",
            "package": "com.target.ui",
            "content-desc": "",
            "checkable": "false",
            "checked": "false",
            "clickable": "true",
            "enabled": "true",
            "focusable": "true",
            "focused": "false",
            "scrollable": "false",
            "long-clickable": "false",
            "password": "false",
            "selected": "false",
            "visible-to-user": "true",
            "bounds": "[636,56][768,152]",
            "drawing-order": "1",
            "hint": "",
            "display-id": "0"
        }
    },
    {
        "type": "click",
        "element": {
            "index": "0",
            "text": "Chat now",
            "resource-id": "",
            "class": "android.widget.TextView",
            "package": "com.target.ui",
            "content-desc": "",
            "checkable": "false",
            "checked": "false",
            "clickable": "false",
            "enabled": "true",
            "focusable": "false",
            "focused": "false",
            "scrollable": "false",
            "long-clickable": "false",
            "password": "false",
            "selected": "false",
            "visible-to-user": "true",
            "bounds": "[615,951][736,986]",
            "drawing-order": "0",
            "hint": "",
            "display-id": "0"
        }
    },
    {
        "type": "click",
        "element": {
            "index": "0",
            "text": "",
            "resource-id": "",
            "class": "android.widget.FrameLayout",
            "package": "com.target.ui",
            "content-desc": "",
            "checkable": "false",
            "checked": "false",
            "clickable": "false",
            "enabled": "true",
            "focusable": "false",
            "focused": "false",
            "scrollable": "false",
            "long-clickable": "false",
            "password": "false",
            "selected": "false",
            "visible-to-user": "true",
            "bounds": "[32,339][736,425]",
            "drawing-order": "1",
            "hint": "",
            "display-id": "0"
        }
    },
    {
        "type": "input",
        "message": "test",
        "element": {
            "index": "4",
            "text": "",
            "resource-id": "com.google.android.inputmethod.latin:id/key_pos_0_4",
            "class": "android.widget.FrameLayout",
            "package": "com.google.android.inputmethod.latin",
            "content-desc": "t",
            "checkable": "false",
            "checked": "false",
            "clickable": "true",
            "enabled": "true",
            "focusable": "true",
            "focused": "false",
            "scrollable": "false",
            "long-clickable": "true",
            "password": "false",
            "selected": "false",
            "visible-to-user": "true",
            "bounds": "[308,786][384,887]",
            "drawing-order": "5",
            "hint": "",
            "display-id": "0"
        }
    },
    {
        "type": "click",
        "element": {
            "index": "6",
            "text": "Start chat",
            "resource-id": "com.target.ui:id/bvStart",
            "class": "android.widget.Button",
            "package": "com.target.ui",
            "content-desc": "",
            "checkable": "false",
            "checked": "false",
            "clickable": "true",
            "enabled": "true",
            "focusable": "true",
            "focused": "false",
            "scrollable": "false",
            "long-clickable": "false",
            "password": "false",
            "selected": "false",
            "visible-to-user": "true",
            "bounds": "[32,973][736,1069]",
            "drawing-order": "9",
            "hint": "",
            "display-id": "0"
        }
    },
    {
        "type": "stop",
        "element": null
    }
]