<?xml version='1.0' encoding='UTF-8' standalone='yes' ?>
<hierarchy rotation="0">
  <node index="0" text="" resource-id="com.android.systemui:id/navigation_bar_frame" class="android.widget.FrameLayout" package="com.android.systemui" content-desc="" checkable="false" checked="false" clickable="false" enabled="true" focusable="false" focused="false" scrollable="false" long-clickable="false" password="false" selected="false" visible-to-user="true" bounds="[0,1184][768,1280]" drawing-order="0" hint="" display-id="0">
    <node index="0" text="" resource-id="com.android.systemui:id/navigation_bar_view" class="android.widget.FrameLayout" package="com.android.systemui" content-desc="" checkable="false" checked="false" clickable="false" enabled="true" focusable="false" focused="false" scrollable="false" long-clickable="false" password="false" selected="false" visible-to-user="true" bounds="[0,1184][768,1280]" drawing-order="1" hint="" display-id="0">
      <node index="0" text="" resource-id="com.android.systemui:id/navigation_inflater" class="android.widget.FrameLayout" package="com.android.systemui" content-desc="" checkable="false" checked="false" clickable="false" enabled="true" focusable="false" focused="false" scrollable="false" long-clickable="false" password="false" selected="false" visible-to-user="true" bounds="[0,1184][768,1280]" drawing-order="1" hint="" display-id="0">
        <node index="0" text="" resource-id="com.android.systemui:id/horizontal" class="android.widget.FrameLayout" package="com.android.systemui" content-desc="" checkable="false" checked="false" clickable="false" enabled="true" focusable="false" focused="false" scrollable="false" long-clickable="false" password="false" selected="false" visible-to-user="true" bounds="[0,1184][768,1280]" drawing-order="1" hint="" display-id="0">
          <node index="0" text="" resource-id="com.android.systemui:id/nav_buttons" class="android.widget.FrameLayout" package="com.android.systemui" content-desc="" checkable="false" checked="false" clickable="false" enabled="true" focusable="false" focused="false" scrollable="false" long-clickable="false" password="false" selected="false" visible-to-user="true" bounds="[16,1184][752,1280]" drawing-order="1" hint="" display-id="0">
            <node index="0" text="" resource-id="com.android.systemui:id/ends_group" class="android.widget.LinearLayout" package="com.android.systemui" content-desc="" checkable="false" checked="false" clickable="false" enabled="true" focusable="false" focused="false" scrollable="false" long-clickable="false" password="false" selected="false" visible-to-user="true" bounds="[16,1184][752,1280]" drawing-order="1" hint="" display-id="0">
              <node index="0" text="" resource-id="" class="android.widget.RelativeLayout" package="com.android.systemui" content-desc="" checkable="false" checked="false" clickable="false" enabled="true" focusable="false" focused="false" scrollable="false" long-clickable="false" password="false" selected="false" visible-to-user="true" bounds="[16,1184][89,1280]" drawing-order="1" hint="" display-id="0" />
              <node index="1" text="" resource-id="" class="android.widget.RelativeLayout" package="com.android.systemui" content-desc="" checkable="false" checked="false" clickable="false" enabled="true" focusable="false" focused="false" scrollable="false" long-clickable="false" password="false" selected="false" visible-to-user="true" bounds="[89,1184][236,1280]" drawing-order="2" hint="" display-id="0">
                <node index="0" text="" resource-id="com.android.systemui:id/back" class="android.widget.ImageView" package="com.android.systemui" content-desc="Back" checkable="false" checked="false" clickable="true" enabled="true" focusable="true" focused="false" scrollable="false" long-clickable="false" password="false" selected="false" visible-to-user="true" bounds="[89,1184][236,1280]" drawing-order="1" hint="" display-id="0" />
              </node>
              <node index="2" text="" resource-id="" class="android.widget.RelativeLayout" package="com.android.systemui" content-desc="" checkable="false" checked="false" clickable="false" enabled="true" focusable="false" focused="false" scrollable="false" long-clickable="false" password="false" selected="false" visible-to-user="true" bounds="[530,1184][678,1280]" drawing-order="4" hint="" display-id="0">
                <node index="0" text="" resource-id="com.android.systemui:id/recent_apps" class="android.widget.ImageView" package="com.android.systemui" content-desc="Overview" checkable="false" checked="false" clickable="true" enabled="true" focusable="true" focused="false" scrollable="false" long-clickable="false" password="false" selected="false" visible-to-user="true" bounds="[530,1184][678,1280]" drawing-order="1" hint="" display-id="0" />
              </node>
              <node index="3" text="" resource-id="" class="android.widget.RelativeLayout" package="com.android.systemui" content-desc="" checkable="false" checked="false" clickable="false" enabled="true" focusable="false" focused="false" scrollable="false" long-clickable="false" password="false" selected="false" visible-to-user="true" bounds="[678,1184][752,1280]" drawing-order="5" hint="" display-id="0" />
            </node>
            <node index="1" text="" resource-id="com.android.systemui:id/center_group" class="android.widget.LinearLayout" package="com.android.systemui" content-desc="" checkable="false" checked="false" clickable="false" enabled="true" focusable="false" focused="false" scrollable="false" long-clickable="false" password="false" selected="false" visible-to-user="true" bounds="[304,1184][464,1280]" drawing-order="2" hint="" display-id="0">
              <node index="0" text="" resource-id="com.android.systemui:id/home" class="android.widget.FrameLayout" package="com.android.systemui" content-desc="" checkable="false" checked="false" clickable="true" enabled="true" focusable="true" focused="false" scrollable="false" long-clickable="true" password="false" selected="false" visible-to-user="true" bounds="[304,1184][464,1280]" drawing-order="1" hint="" display-id="0">
                <node index="0" text="" resource-id="com.android.systemui:id/home_button" class="android.widget.ImageView" package="com.android.systemui" content-desc="Home" checkable="false" checked="false" clickable="true" enabled="true" focusable="true" focused="false" scrollable="false" long-clickable="true" password="false" selected="false" visible-to-user="true" bounds="[304,1184][464,1280]" drawing-order="5" hint="" display-id="0" />
                <node index="1" text="" resource-id="" class="android.widget.RelativeLayout" package="com.android.systemui" content-desc="" checkable="false" checked="false" clickable="false" enabled="true" focusable="false" focused="false" scrollable="false" long-clickable="false" password="false" selected="false" visible-to-user="true" bounds="[304,1184][464,1280]" drawing-order="1" hint="" display-id="0" />
                <node index="2" text="" resource-id="com.android.systemui:id/white_cutout" class="android.widget.ImageView" package="com.android.systemui" content-desc="" checkable="false" checked="false" clickable="false" enabled="true" focusable="false" focused="false" scrollable="false" long-clickable="false" password="false" selected="false" visible-to-user="true" bounds="[352,1200][416,1264]" drawing-order="3" hint="" display-id="0" />
                <node index="3" text="" resource-id="com.android.systemui:id/white" class="android.widget.ImageView" package="com.android.systemui" content-desc="" checkable="false" checked="false" clickable="false" enabled="true" focusable="false" focused="false" scrollable="false" long-clickable="false" password="false" selected="false" visible-to-user="true" bounds="[352,1200][416,1264]" drawing-order="4" hint="" display-id="0" />
              </node>
            </node>
          </node>
        </node>
      </node>
    </node>
  </node>
  <node index="0" text="" resource-id="" class="android.widget.FrameLayout" package="com.android.systemui" content-desc="" checkable="false" checked="false" clickable="false" enabled="true" focusable="false" focused="false" scrollable="false" long-clickable="false" password="false" selected="false" visible-to-user="true" bounds="[0,0][768,48]" drawing-order="0" hint="" display-id="0">
    <node index="0" text="" resource-id="com.android.systemui:id/status_bar_launch_animation_container" class="android.widget.FrameLayout" package="com.android.systemui" content-desc="" checkable="false" checked="false" clickable="false" enabled="true" focusable="false" focused="false" scrollable="false" long-clickable="false" password="false" selected="false" visible-to-user="true" bounds="[0,0][768,48]" drawing-order="1" hint="" display-id="0" />
    <node index="1" text="" resource-id="com.android.systemui:id/status_bar_container" class="android.widget.FrameLayout" package="com.android.systemui" content-desc="" checkable="false" checked="false" clickable="false" enabled="true" focusable="false" focused="false" scrollable="false" long-clickable="false" password="false" selected="false" visible-to-user="true" bounds="[0,0][768,48]" drawing-order="2" hint="" display-id="0">
      <node index="0" text="" resource-id="com.android.systemui:id/status_bar" class="android.widget.FrameLayout" package="com.android.systemui" content-desc="" checkable="false" checked="false" clickable="false" enabled="true" focusable="false" focused="false" scrollable="false" long-clickable="false" password="false" selected="false" visible-to-user="true" bounds="[0,0][768,48]" drawing-order="1" hint="" display-id="0">
        <node index="0" text="" resource-id="com.android.systemui:id/status_bar_contents" class="android.widget.LinearLayout" package="com.android.systemui" content-desc="" checkable="false" checked="false" clickable="false" enabled="true" focusable="false" focused="false" scrollable="false" long-clickable="false" password="false" selected="false" visible-to-user="true" bounds="[0,0][728,48]" drawing-order="2" hint="" display-id="0">
          <node index="0" text="" resource-id="" class="android.widget.FrameLayout" package="com.android.systemui" content-desc="" checkable="false" checked="false" clickable="false" enabled="true" focusable="false" focused="false" scrollable="false" long-clickable="false" password="false" selected="false" visible-to-user="true" bounds="[16,0][364,48]" drawing-order="1" hint="" display-id="0">
            <node index="0" text="" resource-id="com.android.systemui:id/status_bar_left_side" class="android.widget.LinearLayout" package="com.android.systemui" content-desc="" checkable="false" checked="false" clickable="false" enabled="true" focusable="false" focused="false" scrollable="false" long-clickable="false" password="false" selected="false" visible-to-user="true" bounds="[16,0][364,48]" drawing-order="2" hint="" display-id="0">
              <node index="0" text="12:26" resource-id="com.android.systemui:id/clock" class="android.widget.TextView" package="com.android.systemui" content-desc="12:26 AM" checkable="false" checked="false" clickable="false" enabled="true" focusable="false" focused="false" scrollable="false" long-clickable="false" password="false" selected="false" visible-to-user="true" bounds="[16,0][101,48]" drawing-order="2" hint="" display-id="0" />
              <node index="1" text="" resource-id="com.android.systemui:id/notification_icon_area" class="android.widget.FrameLayout" package="com.android.systemui" content-desc="" checkable="false" checked="false" clickable="false" enabled="true" focusable="false" focused="false" scrollable="false" long-clickable="false" password="false" selected="false" visible-to-user="true" bounds="[101,0][364,48]" drawing-order="4" hint="" display-id="0">
                <node index="0" text="" resource-id="com.android.systemui:id/notification_icon_area_inner" class="android.widget.LinearLayout" package="com.android.systemui" content-desc="" checkable="false" checked="false" clickable="false" enabled="true" focusable="false" focused="false" scrollable="false" long-clickable="false" password="false" selected="false" visible-to-user="true" bounds="[101,0][364,48]" drawing-order="1" hint="" display-id="0">
                  <node index="0" text="" resource-id="com.android.systemui:id/notificationIcons" class="android.widget.FrameLayout" package="com.android.systemui" content-desc="" checkable="false" checked="false" clickable="false" enabled="true" focusable="false" focused="false" scrollable="false" long-clickable="false" password="false" selected="false" visible-to-user="true" bounds="[101,0][364,48]" drawing-order="1" hint="" display-id="0">
                    <node index="0" text="" resource-id="" class="android.widget.ImageView" package="com.android.systemui" content-desc="ATX notification: UIAutomator" checkable="false" checked="false" clickable="false" enabled="true" focusable="false" focused="false" scrollable="false" long-clickable="false" password="false" selected="false" visible-to-user="true" bounds="[101,0][145,48]" drawing-order="1" hint="" display-id="0" />
                  </node>
                </node>
              </node>
            </node>
          </node>
          <node index="1" text="" resource-id="com.android.systemui:id/system_icon_area" class="android.widget.LinearLayout" package="com.android.systemui" content-desc="" checkable="false" checked="false" clickable="false" enabled="true" focusable="false" focused="false" scrollable="false" long-clickable="false" password="false" selected="false" visible-to-user="true" bounds="[364,0][712,48]" drawing-order="4" hint="" display-id="0">
            <node index="0" text="" resource-id="com.android.systemui:id/system_icons" class="android.widget.LinearLayout" package="com.android.systemui" content-desc="" checkable="false" checked="false" clickable="false" enabled="true" focusable="false" focused="false" scrollable="false" long-clickable="false" password="false" selected="false" visible-to-user="true" bounds="[364,0][712,48]" drawing-order="1" hint="" display-id="0">
              <node index="0" text="" resource-id="com.android.systemui:id/statusIcons" class="android.widget.LinearLayout" package="com.android.systemui" content-desc="" checkable="false" checked="false" clickable="false" enabled="true" focusable="false" focused="false" scrollable="false" long-clickable="false" password="false" selected="false" visible-to-user="true" bounds="[364,0][696,48]" drawing-order="1" hint="" display-id="0">
                <node index="0" text="" resource-id="com.android.systemui:id/wifi_combo" class="android.widget.FrameLayout" package="com.android.systemui" content-desc="Wifi signal full." checkable="false" checked="false" clickable="false" enabled="true" focusable="false" focused="false" scrollable="false" long-clickable="false" password="false" selected="false" visible-to-user="true" bounds="[619,2][654,46]" drawing-order="14" hint="" display-id="0">
                  <node index="0" text="" resource-id="com.android.systemui:id/wifi_group" class="android.widget.LinearLayout" package="com.android.systemui" content-desc="" checkable="false" checked="false" clickable="false" enabled="true" focusable="false" focused="false" scrollable="false" long-clickable="false" password="false" selected="false" visible-to-user="true" bounds="[624,2][654,46]" drawing-order="1" hint="" display-id="0">
                    <node index="0" text="" resource-id="com.android.systemui:id/wifi_combo" class="android.widget.FrameLayout" package="com.android.systemui" content-desc="" checkable="false" checked="false" clickable="false" enabled="true" focusable="false" focused="false" scrollable="false" long-clickable="false" password="false" selected="false" visible-to-user="true" bounds="[624,9][654,39]" drawing-order="2" hint="" display-id="0">
                      <node index="0" text="" resource-id="com.android.systemui:id/wifi_signal" class="android.widget.ImageView" package="com.android.systemui" content-desc="" checkable="false" checked="false" clickable="false" enabled="true" focusable="false" focused="false" scrollable="false" long-clickable="false" password="false" selected="false" visible-to-user="true" bounds="[624,9][654,39]" drawing-order="1" hint="" display-id="0" />
                    </node>
                  </node>
                </node>
                <node index="1" text="" resource-id="com.android.systemui:id/mobile_combo" class="android.widget.FrameLayout" package="com.android.systemui" content-desc="Phone three bars." checkable="false" checked="false" clickable="false" enabled="true" focusable="false" focused="false" scrollable="false" long-clickable="false" password="false" selected="false" visible-to-user="true" bounds="[654,2][684,46]" drawing-order="16" hint="" display-id="0">
                  <node index="0" text="" resource-id="com.android.systemui:id/mobile_group" class="android.widget.LinearLayout" package="com.android.systemui" content-desc="" checkable="false" checked="false" clickable="false" enabled="true" focusable="false" focused="false" scrollable="false" long-clickable="false" password="false" selected="false" visible-to-user="true" bounds="[654,2][684,46]" drawing-order="1" hint="" display-id="0">
                    <node index="0" text="" resource-id="" class="android.widget.FrameLayout" package="com.android.systemui" content-desc="" checkable="false" checked="false" clickable="false" enabled="true" focusable="false" focused="false" scrollable="false" long-clickable="false" password="false" selected="false" visible-to-user="true" bounds="[654,9][684,39]" drawing-order="4" hint="" display-id="0">
                      <node index="0" text="" resource-id="com.android.systemui:id/mobile_signal" class="android.widget.ImageView" package="com.android.systemui" content-desc="" checkable="false" checked="false" clickable="false" enabled="true" focusable="false" focused="false" scrollable="false" long-clickable="false" password="false" selected="false" visible-to-user="true" bounds="[654,9][684,39]" drawing-order="1" hint="" display-id="0" />
                    </node>
                  </node>
                </node>
              </node>
              <node index="1" text="" resource-id="com.android.systemui:id/battery" class="android.widget.LinearLayout" package="com.android.systemui" content-desc="Battery 100 percent." checkable="false" checked="false" clickable="false" enabled="true" focusable="false" focused="false" scrollable="false" long-clickable="false" password="false" selected="false" visible-to-user="true" bounds="[696,0][712,48]" drawing-order="2" hint="" display-id="0">
                <node index="0" text="" resource-id="" class="android.widget.ImageView" package="com.android.systemui" content-desc="" checkable="false" checked="false" clickable="false" enabled="true" focusable="false" focused="false" scrollable="false" long-clickable="false" password="false" selected="false" visible-to-user="true" bounds="[696,11][712,37]" drawing-order="1" hint="" display-id="0" />
              </node>
            </node>
          </node>
        </node>
      </node>
    </node>
  </node>
  <node index="0" text="" resource-id="" class="android.widget.FrameLayout" package="com.linkedin.android" content-desc="" checkable="false" checked="false" clickable="false" enabled="true" focusable="false" focused="false" scrollable="false" long-clickable="false" password="false" selected="false" visible-to-user="true" bounds="[0,0][768,1280]" drawing-order="0" hint="" display-id="0">
    <node index="0" text="" resource-id="" class="android.widget.LinearLayout" package="com.linkedin.android" content-desc="" checkable="false" checked="false" clickable="false" enabled="true" focusable="false" focused="false" scrollable="false" long-clickable="false" password="false" selected="false" visible-to-user="true" bounds="[0,0][768,1184]" drawing-order="1" hint="" display-id="0">
      <node index="0" text="" resource-id="" class="android.widget.FrameLayout" package="com.linkedin.android" content-desc="" checkable="false" checked="false" clickable="false" enabled="true" focusable="false" focused="false" scrollable="false" long-clickable="false" password="false" selected="false" visible-to-user="true" bounds="[0,48][768,1184]" drawing-order="2" hint="" display-id="0">
        <node index="0" text="" resource-id="com.linkedin.android:id/action_bar_root" class="android.widget.LinearLayout" package="com.linkedin.android" content-desc="" checkable="false" checked="false" clickable="false" enabled="true" focusable="false" focused="false" scrollable="false" long-clickable="false" password="false" selected="false" visible-to-user="true" bounds="[0,48][768,1184]" drawing-order="1" hint="" display-id="0">
          <node index="0" text="" resource-id="android:id/content" class="android.widget.FrameLayout" package="com.linkedin.android" content-desc="" checkable="false" checked="false" clickable="false" enabled="true" focusable="false" focused="false" scrollable="false" long-clickable="false" password="false" selected="false" visible-to-user="true" bounds="[0,48][768,1184]" drawing-order="2" hint="" display-id="0">
            <node index="0" text="" resource-id="com.linkedin.android:id/infra_activity_container" class="android.widget.FrameLayout" package="com.linkedin.android" content-desc="" checkable="false" checked="false" clickable="false" enabled="true" focusable="false" focused="false" scrollable="false" long-clickable="false" password="false" selected="false" visible-to-user="true" bounds="[0,48][768,1184]" drawing-order="1" hint="" display-id="0">
              <node index="0" text="" resource-id="com.linkedin.android:id/home_drawer_layout" class="androidx.drawerlayout.widget.DrawerLayout" package="com.linkedin.android" content-desc="" checkable="false" checked="false" clickable="false" enabled="true" focusable="false" focused="false" scrollable="false" long-clickable="false" password="false" selected="false" visible-to-user="true" bounds="[0,48][768,1184]" drawing-order="1" hint="" display-id="0">
                <node index="0" text="" resource-id="com.linkedin.android:id/main_content" class="android.widget.ScrollView" package="com.linkedin.android" content-desc="" checkable="false" checked="false" clickable="false" enabled="true" focusable="false" focused="false" scrollable="true" long-clickable="false" password="false" selected="false" visible-to-user="true" bounds="[0,48][768,1184]" drawing-order="1" hint="" display-id="0">
                  <node index="0" text="" resource-id="com.linkedin.android:id/app_bar_layout" class="android.widget.LinearLayout" package="com.linkedin.android" content-desc="" checkable="false" checked="false" clickable="false" enabled="true" focusable="false" focused="false" scrollable="false" long-clickable="false" password="false" selected="false" visible-to-user="true" bounds="[0,48][768,136]" drawing-order="1" hint="" display-id="0">
                    <node index="0" text="" resource-id="com.linkedin.android:id/collapsing_toolbar_layout" class="android.widget.FrameLayout" package="com.linkedin.android" content-desc="" checkable="false" checked="false" clickable="false" enabled="true" focusable="false" focused="false" scrollable="false" long-clickable="false" password="false" selected="false" visible-to-user="true" bounds="[0,48][768,136]" drawing-order="1" hint="" display-id="0">
                      <node index="0" text="" resource-id="com.linkedin.android:id/home_top_bar" class="android.widget.LinearLayout" package="com.linkedin.android" content-desc="" checkable="false" checked="false" clickable="false" enabled="true" focusable="false" focused="false" scrollable="false" long-clickable="false" password="false" selected="false" visible-to-user="true" bounds="[0,48][768,136]" drawing-order="1" hint="" display-id="0">
                        <node index="0" text="" resource-id="com.linkedin.android:id/me_launcher_container" class="android.widget.Button" package="com.linkedin.android" content-desc="Menu button: Access my profile and other navigation links" checkable="false" checked="false" clickable="true" enabled="true" focusable="true" focused="false" scrollable="false" long-clickable="false" password="false" selected="false" visible-to-user="true" bounds="[0,48][120,136]" drawing-order="1" hint="" display-id="0">
                          <node index="0" text="" resource-id="com.linkedin.android:id/me_launcher" class="android.widget.ImageView" package="com.linkedin.android" content-desc="My Profile and Communities" checkable="false" checked="false" clickable="false" enabled="true" focusable="false" focused="false" scrollable="false" long-clickable="false" password="false" selected="false" visible-to-user="true" bounds="[0,48][120,136]" drawing-order="1" hint="" display-id="0" />
                        </node>
                        <node index="1" text="" resource-id="" class="android.widget.LinearLayout" package="com.linkedin.android" content-desc="" checkable="false" checked="false" clickable="false" enabled="true" focusable="false" focused="false" scrollable="false" long-clickable="false" password="false" selected="false" visible-to-user="true" bounds="[120,48][552,136]" drawing-order="2" hint="" display-id="0">
                          <node index="0" text="" resource-id="com.linkedin.android:id/search_open_bar_box" class="android.widget.LinearLayout" package="com.linkedin.android" content-desc="" checkable="false" checked="false" clickable="true" enabled="true" focusable="true" focused="false" scrollable="false" long-clickable="false" password="false" selected="false" visible-to-user="true" bounds="[120,48][552,136]" drawing-order="1" hint="" display-id="0">
                            <node index="0" text="" resource-id="com.linkedin.android:id/search_bar" class="android.widget.Button" package="com.linkedin.android" content-desc="Search jobs" checkable="false" checked="false" clickable="false" enabled="true" focusable="false" focused="false" scrollable="false" long-clickable="false" password="false" selected="false" visible-to-user="true" bounds="[120,60][552,124]" drawing-order="1" hint="" display-id="0">
                              <node index="0" text="" resource-id="com.linkedin.android:id/search_icon" class="android.widget.ImageView" package="com.linkedin.android" content-desc="" checkable="false" checked="false" clickable="false" enabled="true" focusable="false" focused="false" scrollable="false" long-clickable="false" password="false" selected="false" visible-to-user="true" bounds="[136,76][168,108]" drawing-order="1" hint="" display-id="0" />
                              <node index="1" text="Search jobs" resource-id="com.linkedin.android:id/search_bar_text" class="android.widget.TextView" package="com.linkedin.android" content-desc="" checkable="false" checked="false" clickable="false" enabled="true" focusable="false" focused="false" scrollable="false" long-clickable="false" password="false" selected="false" visible-to-user="true" bounds="[176,70][544,113]" drawing-order="2" hint="" display-id="0" />
                            </node>
                          </node>
                        </node>
                        <node index="2" text="" resource-id="com.linkedin.android:id/home_scalable_nav_image_button" class="android.widget.ImageButton" package="com.linkedin.android" content-desc="Jobs navigation menu" checkable="false" checked="false" clickable="true" enabled="true" focusable="true" focused="false" scrollable="false" long-clickable="false" password="false" selected="false" visible-to-user="true" bounds="[552,48][648,136]" drawing-order="3" hint="" display-id="0" />
                        <node index="3" text="" resource-id="com.linkedin.android:id/home_messaging" class="android.widget.Button" package="com.linkedin.android" content-desc="messaging" checkable="false" checked="false" clickable="true" enabled="true" focusable="true" focused="false" scrollable="false" long-clickable="false" password="false" selected="false" visible-to-user="true" bounds="[648,48][768,136]" drawing-order="6" hint="" display-id="0">
                          <node index="0" text="" resource-id="com.linkedin.android:id/ad_notification_badge_icon" class="android.widget.ImageView" package="com.linkedin.android" content-desc="" checkable="false" checked="false" clickable="false" enabled="true" focusable="false" focused="false" scrollable="false" long-clickable="false" password="false" selected="false" visible-to-user="true" bounds="[684,68][732,116]" drawing-order="1" hint="" display-id="0" />
                        </node>
                      </node>
                    </node>
                  </node>
                  <node index="1" text="" resource-id="com.linkedin.android:id/home_nav_item_fragment_container" class="android.widget.FrameLayout" package="com.linkedin.android" content-desc="" checkable="false" checked="false" clickable="false" enabled="true" focusable="false" focused="false" scrollable="false" long-clickable="false" password="false" selected="false" visible-to-user="true" bounds="[0,136][768,1184]" drawing-order="2" hint="" display-id="0">
                    <node index="0" text="" resource-id="" class="android.widget.FrameLayout" package="com.linkedin.android" content-desc="" checkable="false" checked="false" clickable="false" enabled="true" focusable="false" focused="false" scrollable="false" long-clickable="false" password="false" selected="false" visible-to-user="true" bounds="[0,136][768,1184]" drawing-order="1" hint="" display-id="0">
                      <node index="0" text="" resource-id="" class="android.widget.FrameLayout" package="com.linkedin.android" content-desc="" checkable="false" checked="false" clickable="false" enabled="true" focusable="false" focused="false" scrollable="false" long-clickable="false" password="false" selected="false" visible-to-user="true" bounds="[0,136][768,1184]" drawing-order="1" hint="" display-id="0">
                        <node index="0" text="" resource-id="" class="android.widget.LinearLayout" package="com.linkedin.android" content-desc="" checkable="false" checked="false" clickable="false" enabled="true" focusable="false" focused="false" scrollable="false" long-clickable="false" password="false" selected="false" visible-to-user="true" bounds="[0,136][768,1184]" drawing-order="1" hint="" display-id="0">
                          <node index="0" text="" resource-id="com.linkedin.android:id/content_state_container" class="android.widget.FrameLayout" package="com.linkedin.android" content-desc="" checkable="false" checked="false" clickable="false" enabled="true" focusable="false" focused="false" scrollable="false" long-clickable="false" password="false" selected="false" visible-to-user="true" bounds="[0,136][768,1184]" drawing-order="1" hint="" display-id="0">
                            <node index="0" text="" resource-id="com.linkedin.android:id/job_home_full_page" class="android.widget.LinearLayout" package="com.linkedin.android" content-desc="" checkable="false" checked="false" clickable="false" enabled="true" focusable="false" focused="false" scrollable="false" long-clickable="false" password="false" selected="false" visible-to-user="true" bounds="[0,136][768,1184]" drawing-order="1" hint="" display-id="0">
                              <node index="0" text="" resource-id="com.linkedin.android:id/swipe_refresh_wrapper" class="android.view.ViewGroup" package="com.linkedin.android" content-desc="" checkable="false" checked="false" clickable="false" enabled="true" focusable="false" focused="false" scrollable="false" long-clickable="false" password="false" selected="false" visible-to-user="true" bounds="[0,136][768,1184]" drawing-order="1" hint="" display-id="0">
                                <node index="0" text="" resource-id="com.linkedin.android:id/job_home_main_content" class="androidx.recyclerview.widget.RecyclerView" package="com.linkedin.android" content-desc="Job home main content" checkable="false" checked="false" clickable="false" enabled="true" focusable="true" focused="false" scrollable="true" long-clickable="false" password="false" selected="false" visible-to-user="true" bounds="[0,136][768,1184]" drawing-order="1" hint="" display-id="0">
                                  <node index="0" text="" resource-id="" class="android.widget.FrameLayout" package="com.linkedin.android" content-desc="" checkable="false" checked="false" clickable="false" enabled="true" focusable="false" focused="false" scrollable="false" long-clickable="false" password="false" selected="false" visible-to-user="true" bounds="[0,136][768,246]" drawing-order="1" hint="" display-id="0">
                                    <node index="0" text="" resource-id="com.linkedin.android:id/scalable_nav_items" class="androidx.recyclerview.widget.RecyclerView" package="com.linkedin.android" content-desc="" checkable="false" checked="false" clickable="false" enabled="true" focusable="true" focused="false" scrollable="false" long-clickable="false" password="false" selected="false" visible-to-user="true" bounds="[0,136][768,246]" drawing-order="1" hint="" display-id="0">
                                      <node index="0" text="" resource-id="com.linkedin.android:id/scalable_nav_item" class="android.widget.Button" package="com.linkedin.android" content-desc="My jobs" checkable="false" checked="false" clickable="true" enabled="true" focusable="true" focused="false" scrollable="false" long-clickable="false" password="false" selected="false" visible-to-user="true" bounds="[24,150][202,230]" drawing-order="1" hint="" display-id="0">
                                        <node index="0" text="My jobs" resource-id="com.linkedin.android:id/scalable_nav_text" class="android.widget.TextView" package="com.linkedin.android" content-desc="" checkable="false" checked="false" clickable="false" enabled="true" focusable="false" focused="false" scrollable="false" long-clickable="false" password="false" selected="false" visible-to-user="true" bounds="[25,153][201,228]" drawing-order="2" hint="" display-id="0" />
                                      </node>
                                      <node index="1" text="" resource-id="com.linkedin.android:id/scalable_nav_item" class="android.widget.Button" package="com.linkedin.android" content-desc="Preferences" checkable="false" checked="false" clickable="true" enabled="true" focusable="true" focused="false" scrollable="false" long-clickable="false" password="false" selected="false" visible-to-user="true" bounds="[217,150][455,230]" drawing-order="2" hint="" display-id="0">
                                        <node index="0" text="Preferences" resource-id="com.linkedin.android:id/scalable_nav_text" class="android.widget.TextView" package="com.linkedin.android" content-desc="" checkable="false" checked="false" clickable="false" enabled="true" focusable="false" focused="false" scrollable="false" long-clickable="false" password="false" selected="false" visible-to-user="true" bounds="[218,153][454,228]" drawing-order="2" hint="" display-id="0" />
                                      </node>
                                      <node index="2" text="" resource-id="com.linkedin.android:id/scalable_nav_item" class="android.widget.Button" package="com.linkedin.android" content-desc="Post a free job" checkable="false" checked="false" clickable="true" enabled="true" focusable="true" focused="false" scrollable="false" long-clickable="false" password="false" selected="false" visible-to-user="true" bounds="[470,150][742,230]" drawing-order="3" hint="" display-id="0">
                                        <node index="0" text="Post a free job" resource-id="com.linkedin.android:id/scalable_nav_text" class="android.widget.TextView" package="com.linkedin.android" content-desc="" checkable="false" checked="false" clickable="false" enabled="true" focusable="false" focused="false" scrollable="false" long-clickable="false" password="false" selected="false" visible-to-user="true" bounds="[471,153][741,228]" drawing-order="2" hint="" display-id="0" />
                                      </node>
                                    </node>
                                  </node>
                                  <node index="2" text="" resource-id="com.linkedin.android:id/growth_launchpad" class="android.view.ViewGroup" package="com.linkedin.android" content-desc="" checkable="false" checked="false" clickable="false" enabled="true" focusable="false" focused="false" scrollable="false" long-clickable="false" password="false" selected="false" visible-to-user="true" bounds="[0,274][768,988]" drawing-order="3" hint="" display-id="0">
                                    <node index="0" text="Privately specify your pay preference" resource-id="com.linkedin.android:id/summary_header" class="android.widget.TextView" package="com.linkedin.android" content-desc="" checkable="false" checked="false" clickable="false" enabled="true" focusable="false" focused="false" scrollable="false" long-clickable="false" password="false" selected="false" visible-to-user="true" bounds="[32,306][672,349]" drawing-order="5" hint="" display-id="0" />
                                    <node index="1" text="" resource-id="com.linkedin.android:id/launchpad_theme_layout" class="android.widget.FrameLayout" package="com.linkedin.android" content-desc="" checkable="false" checked="false" clickable="false" enabled="true" focusable="false" focused="false" scrollable="false" long-clickable="false" password="false" selected="false" visible-to-user="true" bounds="[0,349][768,988]" drawing-order="8" hint="" display-id="0">
                                      <node index="0" text="" resource-id="com.linkedin.android:id/card_frame_layout" class="android.widget.FrameLayout" package="com.linkedin.android" content-desc="" checkable="false" checked="false" clickable="false" enabled="true" focusable="false" focused="false" scrollable="false" long-clickable="false" password="false" selected="false" visible-to-user="true" bounds="[0,373][768,988]" drawing-order="1" hint="" display-id="0">
                                        <node index="0" text="" resource-id="" class="android.widget.LinearLayout" package="com.linkedin.android" content-desc="" checkable="false" checked="false" clickable="false" enabled="true" focusable="false" focused="false" scrollable="false" long-clickable="false" password="false" selected="false" visible-to-user="true" bounds="[0,373][768,988]" drawing-order="1" hint="" display-id="0">
                                          <node index="0" text="" resource-id="com.linkedin.android:id/card_layout_carousel" class="androidx.recyclerview.widget.RecyclerView" package="com.linkedin.android" content-desc="" checkable="false" checked="false" clickable="false" enabled="true" focusable="true" focused="false" scrollable="false" long-clickable="false" password="false" selected="false" visible-to-user="true" bounds="[0,373][768,964]" drawing-order="1" hint="" display-id="0">
                                            <node index="0" text="" resource-id="com.linkedin.android:id/multi_theme_layout_card" class="android.widget.FrameLayout" package="com.linkedin.android" content-desc="" checkable="false" checked="false" clickable="false" enabled="true" focusable="false" focused="false" scrollable="false" long-clickable="false" password="false" selected="false" visible-to-user="true" bounds="[32,381][736,956]" drawing-order="1" hint="" display-id="0">
                                              <node index="0" text="" resource-id="com.linkedin.android:id/growth_launchpad_card_with_inline_action" class="android.view.ViewGroup" package="com.linkedin.android" content-desc="" checkable="false" checked="false" clickable="false" enabled="true" focusable="false" focused="false" scrollable="false" long-clickable="false" password="false" selected="false" visible-to-user="true" bounds="[32,381][736,956]" drawing-order="1" hint="" display-id="0">
                                                <node index="0" text="This data is not visible to others. Learn more" resource-id="com.linkedin.android:id/launchpad_card_title" class="android.widget.TextView" package="com.linkedin.android" content-desc="" checkable="false" checked="false" clickable="false" enabled="true" focusable="false" focused="false" scrollable="false" long-clickable="false" password="false" selected="false" visible-to-user="true" bounds="[64,405][704,443]" drawing-order="2" hint="" display-id="0" />
                                                <node index="1" text="" resource-id="com.linkedin.android:id/launchpad_card_form_container" class="android.view.ViewGroup" package="com.linkedin.android" content-desc="" checkable="false" checked="false" clickable="false" enabled="true" focusable="false" focused="false" scrollable="false" long-clickable="false" password="false" selected="false" visible-to-user="true" bounds="[64,443][704,836]" drawing-order="3" hint="" display-id="0">
                                                  <node index="0" text="" resource-id="com.linkedin.android:id/form_elements" class="androidx.recyclerview.widget.RecyclerView" package="com.linkedin.android" content-desc="" checkable="false" checked="false" clickable="false" enabled="true" focusable="true" focused="false" scrollable="false" long-clickable="false" password="false" selected="false" visible-to-user="true" bounds="[64,443][704,836]" drawing-order="4" hint="" display-id="0">
                                                    <node index="0" text="" resource-id="" class="android.widget.LinearLayout" package="com.linkedin.android" content-desc="" checkable="false" checked="false" clickable="false" enabled="true" focusable="false" focused="false" scrollable="false" long-clickable="false" password="false" selected="false" visible-to-user="true" bounds="[64,443][704,647]" drawing-order="1" hint="" display-id="0">
                                                      <node index="0" text="" resource-id="com.linkedin.android:id/form_elements_in_group" class="androidx.recyclerview.widget.RecyclerView" package="com.linkedin.android" content-desc="" checkable="false" checked="false" clickable="false" enabled="true" focusable="true" focused="false" scrollable="false" long-clickable="false" password="false" selected="false" visible-to-user="true" bounds="[64,443][704,647]" drawing-order="3" hint="" display-id="0">
                                                        <node index="0" text="" resource-id="com.linkedin.android:id/form_text_input_dash_container" class="android.widget.LinearLayout" package="com.linkedin.android" content-desc="" checkable="false" checked="false" clickable="false" enabled="true" focusable="false" focused="false" scrollable="false" long-clickable="false" password="false" selected="false" visible-to-user="true" bounds="[64,443][704,647]" drawing-order="1" hint="" display-id="0">
                                                          <node index="0" text="Minimum base pay (in USD)*" resource-id="com.linkedin.android:id/form_text_input_header" class="android.widget.TextView" package="com.linkedin.android" content-desc="Minimum base pay (in USD)*, Required" checkable="false" checked="false" clickable="true" enabled="true" focusable="true" focused="false" scrollable="false" long-clickable="true" password="false" selected="false" visible-to-user="true" bounds="[64,467][421,505]" drawing-order="1" hint="" display-id="0" />
                                                          <node index="1" text="" resource-id="com.linkedin.android:id/form_text_input_dash" class="android.widget.LinearLayout" package="com.linkedin.android" content-desc="" checkable="false" checked="false" clickable="false" enabled="true" focusable="false" focused="false" scrollable="false" long-clickable="false" password="false" selected="false" visible-to-user="true" bounds="[64,497][704,623]" drawing-order="2" hint="" display-id="0">
                                                            <node index="0" text="" resource-id="" class="android.widget.FrameLayout" package="com.linkedin.android" content-desc="" checkable="false" checked="false" clickable="false" enabled="true" focusable="false" focused="false" scrollable="false" long-clickable="false" password="false" selected="false" visible-to-user="true" bounds="[64,497][704,582]" drawing-order="1" hint="" display-id="0">
                                                              <node index="0" text="Example: $50,000" resource-id="com.linkedin.android:id/form_edit_text_dash" class="android.widget.EditText" package="com.linkedin.android" content-desc="" checkable="false" checked="false" clickable="true" enabled="true" focusable="true" focused="false" scrollable="false" long-clickable="true" password="false" selected="false" visible-to-user="true" bounds="[64,497][704,582]" drawing-order="1" hint="" display-id="0" />
                                                            </node>
                                                            <node index="1" text="" resource-id="" class="android.widget.LinearLayout" package="com.linkedin.android" content-desc="" checkable="false" checked="false" clickable="false" enabled="true" focusable="false" focused="false" scrollable="false" long-clickable="false" password="false" selected="false" visible-to-user="true" bounds="[64,582][704,623]" drawing-order="2" hint="" display-id="0">
                                                              <node index="0" text="" resource-id="" class="android.widget.FrameLayout" package="com.linkedin.android" content-desc="" checkable="false" checked="false" clickable="false" enabled="true" focusable="false" focused="false" scrollable="false" long-clickable="false" password="false" selected="false" visible-to-user="true" bounds="[72,590][696,623]" drawing-order="1" hint="" display-id="0">
                                                                <node index="0" text="Excludes stock, bonuses, tips, etc." resource-id="com.linkedin.android:id/textinput_helper_text" class="android.widget.TextView" package="com.linkedin.android" content-desc="" checkable="false" checked="false" clickable="false" enabled="true" focusable="false" focused="false" scrollable="false" long-clickable="false" password="false" selected="false" visible-to-user="true" bounds="[72,590][696,623]" drawing-order="1" hint="" display-id="0" />
                                                              </node>
                                                            </node>
                                                          </node>
                                                        </node>
                                                      </node>
                                                    </node>
                                                    <node index="1" text="" resource-id="" class="android.widget.LinearLayout" package="com.linkedin.android" content-desc="" checkable="false" checked="false" clickable="false" enabled="true" focusable="false" focused="false" scrollable="false" long-clickable="false" password="false" selected="false" visible-to-user="true" bounds="[64,647][704,836]" drawing-order="2" hint="" display-id="0">
                                                      <node index="0" text="" resource-id="com.linkedin.android:id/form_elements_in_group" class="androidx.recyclerview.widget.RecyclerView" package="com.linkedin.android" content-desc="" checkable="false" checked="false" clickable="false" enabled="true" focusable="true" focused="false" scrollable="false" long-clickable="false" password="false" selected="false" visible-to-user="true" bounds="[64,647][704,836]" drawing-order="3" hint="" display-id="0">
                                                        <node index="0" text="" resource-id="" class="android.widget.LinearLayout" package="com.linkedin.android" content-desc="" checkable="false" checked="false" clickable="false" enabled="true" focusable="false" focused="false" scrollable="false" long-clickable="false" password="false" selected="false" visible-to-user="true" bounds="[64,647][704,836]" drawing-order="1" hint="" display-id="0">
                                                          <node index="0" text="Pay period*" resource-id="com.linkedin.android:id/form_dropdown_header" class="android.widget.TextView" package="com.linkedin.android" content-desc="Pay period*, Required" checkable="false" checked="false" clickable="true" enabled="true" focusable="true" focused="false" scrollable="false" long-clickable="true" password="false" selected="false" visible-to-user="true" bounds="[64,671][208,709]" drawing-order="1" hint="" display-id="0" />
                                                          <node index="1" text="" resource-id="com.linkedin.android:id/form_bottomsheet_layout" class="android.widget.LinearLayout" package="com.linkedin.android" content-desc="" checkable="false" checked="false" clickable="true" enabled="true" focusable="true" focused="false" scrollable="false" long-clickable="false" password="false" selected="false" visible-to-user="true" bounds="[64,693][704,812]" drawing-order="2" hint="" display-id="0">
                                                            <node index="0" text="" resource-id="" class="android.widget.FrameLayout" package="com.linkedin.android" content-desc="" checkable="false" checked="false" clickable="false" enabled="true" focusable="false" focused="false" scrollable="false" long-clickable="false" password="false" selected="false" visible-to-user="true" bounds="[64,722][704,812]" drawing-order="1" hint="" display-id="0">
                                                              <node index="0" text="Select type" resource-id="com.linkedin.android:id/form_bottomsheet_input" class="android.widget.Button" package="com.linkedin.android" content-desc="" checkable="false" checked="false" clickable="true" enabled="true" focusable="false" focused="false" scrollable="false" long-clickable="true" password="false" selected="false" visible-to-user="true" bounds="[64,722][704,812]" drawing-order="1" hint="" display-id="0" />
                                                            </node>
                                                          </node>
                                                        </node>
                                                      </node>
                                                    </node>
                                                  </node>
                                                </node>
                                                <node index="2" text="" resource-id="com.linkedin.android:id/cta_list" class="androidx.recyclerview.widget.RecyclerView" package="com.linkedin.android" content-desc="" checkable="false" checked="false" clickable="false" enabled="true" focusable="true" focused="false" scrollable="false" long-clickable="false" password="false" selected="false" visible-to-user="true" bounds="[32,836][736,932]" drawing-order="4" hint="" display-id="0">
                                                  <node index="0" text="" resource-id="" class="android.view.ViewGroup" package="com.linkedin.android" content-desc="" checkable="false" checked="false" clickable="false" enabled="true" focusable="false" focused="false" scrollable="false" long-clickable="false" password="false" selected="false" visible-to-user="true" bounds="[32,836][736,932]" drawing-order="1" hint="" display-id="0">
                                                    <node index="0" text="Add pay preference" resource-id="com.linkedin.android:id/launchpad_card_cta_primary_default_or_muted" class="android.widget.Button" package="com.linkedin.android" content-desc="" checkable="false" checked="false" clickable="true" enabled="true" focusable="true" focused="false" scrollable="false" long-clickable="false" password="false" selected="false" visible-to-user="true" bounds="[64,836][704,932]" drawing-order="1" hint="" display-id="0" />
                                                  </node>
                                                </node>
                                              </node>
                                            </node>
                                          </node>
                                          <node index="1" text="" resource-id="com.linkedin.android:id/card_layout_auxiliary_view" class="android.view.View" package="com.linkedin.android" content-desc="" checkable="false" checked="false" clickable="false" enabled="true" focusable="false" focused="false" scrollable="false" long-clickable="false" password="false" selected="false" visible-to-user="true" bounds="[0,964][768,988]" drawing-order="3" hint="" display-id="0" />
                                        </node>
                                      </node>
                                    </node>
                                    <node index="2" text="" resource-id="com.linkedin.android:id/launchpad_dismiss" class="android.widget.ImageButton" package="com.linkedin.android" content-desc="Dismiss" checkable="false" checked="false" clickable="true" enabled="true" focusable="true" focused="false" scrollable="false" long-clickable="false" password="false" selected="false" visible-to-user="true" bounds="[672,274][768,370]" drawing-order="9" hint="" display-id="0" />
                                  </node>
                                  <node index="3" text="" resource-id="" class="android.view.ViewGroup" package="com.linkedin.android" content-desc="" checkable="false" checked="false" clickable="false" enabled="true" focusable="true" focused="false" scrollable="false" long-clickable="false" password="false" selected="false" visible-to-user="true" bounds="[0,1004][768,1098]" drawing-order="4" hint="" display-id="0">
                                    <node index="0" text="Discover top jobs for you" resource-id="com.linkedin.android:id/jobs_home_feed_header_title" class="android.widget.TextView" package="com.linkedin.android" content-desc="" checkable="false" checked="false" clickable="false" enabled="true" focusable="false" focused="false" scrollable="false" long-clickable="false" password="false" selected="false" visible-to-user="true" bounds="[24,1036][744,1090]" drawing-order="3" hint="" display-id="0" />
                                  </node>
                                  <node index="4" text="" resource-id="com.linkedin.android:id/careers_job_item_swipe_container" class="android.widget.FrameLayout" package="com.linkedin.android" content-desc="" checkable="false" checked="false" clickable="true" enabled="true" focusable="true" focused="false" scrollable="false" long-clickable="false" password="false" selected="false" visible-to-user="true" bounds="[0,1098][768,1184]" drawing-order="5" hint="" display-id="0">
                                    <node index="0" text="" resource-id="com.linkedin.android:id/careers_job_item_root" class="android.view.ViewGroup" package="com.linkedin.android" content-desc="Data Analyst, Verified, Promoted, Ascendion, California, United States (Remote), $90K/yr - $100K/yr  401(k), Medical, Vision, Dental, +1 benefit, Actively recruiting, Promoted  . Easy Apply, Button" checkable="false" checked="false" clickable="true" enabled="true" focusable="true" focused="false" scrollable="false" long-clickable="false" password="false" selected="false" visible-to-user="true" bounds="[0,1098][768,1184]" drawing-order="1" hint="" display-id="0">
                                      <node index="0" text="" resource-id="com.linkedin.android:id/careers_job_item_entity_lockup" class="android.view.ViewGroup" package="com.linkedin.android" content-desc="" checkable="false" checked="false" clickable="false" enabled="true" focusable="true" focused="false" scrollable="false" long-clickable="false" password="false" selected="false" visible-to-user="true" bounds="[16,1114][672,1184]" drawing-order="1" hint="" display-id="0">
                                        <node index="0" text="" resource-id="com.linkedin.android:id/ad_entity_lockup_image" class="android.widget.ImageView" package="com.linkedin.android" content-desc="Ascendion logo" checkable="false" checked="false" clickable="false" enabled="true" focusable="false" focused="false" scrollable="false" long-clickable="false" password="false" selected="false" visible-to-user="true" bounds="[16,1114][112,1184]" drawing-order="1" hint="" display-id="0" />
                                        <node index="1" text="" resource-id="com.linkedin.android:id/flexboxLayout" class="android.view.ViewGroup" package="com.linkedin.android" content-desc="" checkable="false" checked="false" clickable="false" enabled="true" focusable="false" focused="false" scrollable="false" long-clickable="false" password="false" selected="false" visible-to-user="true" bounds="[128,1114][357,1157]" drawing-order="2" hint="" display-id="0">
                                          <node index="0" text="Data Analystx" resource-id="com.linkedin.android:id/ad_entity_lockup_name" class="android.widget.TextView" package="com.linkedin.android" content-desc="" checkable="false" checked="false" clickable="false" enabled="true" focusable="false" focused="false" scrollable="false" long-clickable="false" password="false" selected="false" visible-to-user="true" bounds="[128,1114][349,1157]" drawing-order="1" hint="" display-id="0" />
                                        </node>
                                        <node index="2" text="Ascendion" resource-id="com.linkedin.android:id/ad_entity_lockup_subtitle" class="android.widget.TextView" package="com.linkedin.android" content-desc="" checkable="false" checked="false" clickable="false" enabled="true" focusable="false" focused="false" scrollable="false" long-clickable="false" password="false" selected="false" visible-to-user="true" bounds="[128,1157][259,1184]" drawing-order="3" hint="" display-id="0" />
                                      </node>
                                      <node index="1" text="" resource-id="com.linkedin.android:id/careers_job_card_actions_container" class="android.widget.LinearLayout" package="com.linkedin.android" content-desc="" checkable="false" checked="false" clickable="false" enabled="true" focusable="false" focused="false" scrollable="false" long-clickable="false" password="false" selected="false" visible-to-user="true" bounds="[672,1114][768,1184]" drawing-order="4" hint="" display-id="0">
                                        <node NAF="true" index="0" text="" resource-id="com.linkedin.android:id/careers_job_card_action_one" class="android.widget.FrameLayout" package="com.linkedin.android" content-desc="" checkable="false" checked="false" clickable="true" enabled="true" focusable="true" focused="false" scrollable="false" long-clickable="false" password="false" selected="false" visible-to-user="true" bounds="[672,1114][768,1184]" drawing-order="1" hint="" display-id="0">
                                          <node index="0" text="" resource-id="com.linkedin.android:id/careers_job_card_action_one_image" class="android.widget.ImageView" package="com.linkedin.android" content-desc="" checkable="false" checked="false" clickable="false" enabled="true" focusable="true" focused="false" scrollable="false" long-clickable="false" password="false" selected="false" visible-to-user="true" bounds="[704,1122][736,1154]" drawing-order="1" hint="" display-id="0" />
                                        </node>
                                      </node>
                                    </node>
                                  </node>
                                </node>
                              </node>
                            </node>
                          </node>
                        </node>
                      </node>
                    </node>
                  </node>
                  <node index="2" text="" resource-id="com.linkedin.android:id/home_bottom_bar" class="android.widget.LinearLayout" package="com.linkedin.android" content-desc="" checkable="false" checked="false" clickable="true" enabled="true" focusable="true" focused="false" scrollable="false" long-clickable="false" password="false" selected="false" visible-to-user="true" bounds="[0,1086][768,1184]" drawing-order="3" hint="" display-id="0">
                    <node index="1" text="" resource-id="com.linkedin.android:id/bb_slim_bottom_bar_shadow" class="android.widget.ImageView" package="com.linkedin.android" content-desc="" checkable="false" checked="false" clickable="false" enabled="true" focusable="false" focused="false" scrollable="false" long-clickable="false" password="false" selected="false" visible-to-user="true" bounds="[0,1086][768,1088]" drawing-order="2" hint="" display-id="0" />
                    <node index="2" text="" resource-id="com.linkedin.android:id/bottom_nav_container" class="android.widget.FrameLayout" package="com.linkedin.android" content-desc="" checkable="false" checked="false" clickable="false" enabled="true" focusable="false" focused="false" scrollable="false" long-clickable="false" password="false" selected="false" visible-to-user="true" bounds="[0,1088][768,1184]" drawing-order="3" hint="" display-id="0">
                      <node index="0" text="" resource-id="com.linkedin.android:id/bb_slim_bottom_bar_item_container" class="android.widget.LinearLayout" package="com.linkedin.android" content-desc="" checkable="false" checked="false" clickable="false" enabled="true" focusable="false" focused="false" scrollable="false" long-clickable="false" password="false" selected="false" visible-to-user="true" bounds="[0,1088][768,1184]" drawing-order="1" hint="" display-id="0">
                        <node index="0" text="" resource-id="com.linkedin.android:id/tab_feed" class="Tab" package="com.linkedin.android" content-desc="Home 1 of 5, new notifications available" checkable="false" checked="false" clickable="true" enabled="true" focusable="true" focused="false" scrollable="false" long-clickable="true" password="false" selected="false" visible-to-user="true" bounds="[4,1088][156,1184]" drawing-order="1" hint="" display-id="0">
                          <node index="0" text="Home" resource-id="com.linkedin.android:id/slim_notification_badge_label" class="android.widget.TextView" package="com.linkedin.android" content-desc="" checkable="false" checked="false" clickable="false" enabled="true" focusable="false" focused="false" scrollable="false" long-clickable="false" password="false" selected="false" visible-to-user="true" bounds="[53,1148][107,1176]" drawing-order="2" hint="" display-id="0" />
                          <node index="1" text="" resource-id="com.linkedin.android:id/slim_notification_badge_icon" class="android.widget.ImageView" package="com.linkedin.android" content-desc="" checkable="false" checked="false" clickable="false" enabled="true" focusable="false" focused="false" scrollable="false" long-clickable="false" password="false" selected="false" visible-to-user="true" bounds="[56,1105][104,1153]" drawing-order="1" hint="" display-id="0" />
                          <node index="2" text="" resource-id="com.linkedin.android:id/slim_notification_coach_mark" class="android.widget.FrameLayout" package="com.linkedin.android" content-desc="" checkable="false" checked="false" clickable="false" enabled="true" focusable="false" focused="false" scrollable="false" long-clickable="false" password="false" selected="false" visible-to-user="true" bounds="[66,1088][134,1151]" drawing-order="3" hint="" display-id="0" />
                          <node index="3" text="" resource-id="com.linkedin.android:id/slim_notification_badge_indeterminate_image" class="android.widget.ImageView" package="com.linkedin.android" content-desc="" checkable="false" checked="false" clickable="false" enabled="true" focusable="false" focused="false" scrollable="false" long-clickable="false" password="false" selected="false" visible-to-user="true" bounds="[82,1101][104,1123]" drawing-order="6" hint="" display-id="0" />
                        </node>
                        <node index="1" text="" resource-id="com.linkedin.android:id/tab_relationships" class="Tab" package="com.linkedin.android" content-desc="My Network 2 of 5" checkable="false" checked="false" clickable="true" enabled="true" focusable="true" focused="false" scrollable="false" long-clickable="true" password="false" selected="false" visible-to-user="true" bounds="[156,1088][308,1184]" drawing-order="2" hint="" display-id="0">
                          <node index="0" text="My Network" resource-id="com.linkedin.android:id/slim_notification_badge_label" class="android.widget.TextView" package="com.linkedin.android" content-desc="" checkable="false" checked="false" clickable="false" enabled="true" focusable="false" focused="false" scrollable="false" long-clickable="false" password="false" selected="false" visible-to-user="true" bounds="[179,1148][285,1176]" drawing-order="2" hint="" display-id="0" />
                          <node index="1" text="" resource-id="com.linkedin.android:id/slim_notification_badge_icon" class="android.widget.ImageView" package="com.linkedin.android" content-desc="" checkable="false" checked="false" clickable="false" enabled="true" focusable="false" focused="false" scrollable="false" long-clickable="false" password="false" selected="false" visible-to-user="true" bounds="[208,1105][256,1153]" drawing-order="1" hint="" display-id="0" />
                          <node index="2" text="" resource-id="com.linkedin.android:id/slim_notification_coach_mark" class="android.widget.FrameLayout" package="com.linkedin.android" content-desc="" checkable="false" checked="false" clickable="false" enabled="true" focusable="false" focused="false" scrollable="false" long-clickable="false" password="false" selected="false" visible-to-user="true" bounds="[218,1088][286,1151]" drawing-order="3" hint="" display-id="0" />
                        </node>
                        <node index="2" text="" resource-id="com.linkedin.android:id/tab_post" class="Tab" package="com.linkedin.android" content-desc="Post 3 of 5" checkable="false" checked="false" clickable="true" enabled="true" focusable="true" focused="false" scrollable="false" long-clickable="true" password="false" selected="false" visible-to-user="true" bounds="[308,1088][460,1184]" drawing-order="3" hint="" display-id="0">
                          <node index="0" text="" resource-id="com.linkedin.android:id/slim_notification_badge_icon" class="android.widget.ImageView" package="com.linkedin.android" content-desc="" checkable="false" checked="false" clickable="false" enabled="true" focusable="false" focused="false" scrollable="false" long-clickable="false" password="false" selected="false" visible-to-user="true" bounds="[360,1105][408,1153]" drawing-order="1" hint="" display-id="0" />
                          <node index="1" text="Post" resource-id="com.linkedin.android:id/slim_notification_badge_label" class="android.widget.TextView" package="com.linkedin.android" content-desc="" checkable="false" checked="false" clickable="false" enabled="true" focusable="false" focused="false" scrollable="false" long-clickable="false" password="false" selected="false" visible-to-user="true" bounds="[364,1148][405,1176]" drawing-order="2" hint="" display-id="0" />
                          <node index="2" text="" resource-id="com.linkedin.android:id/slim_notification_coach_mark" class="android.widget.FrameLayout" package="com.linkedin.android" content-desc="" checkable="false" checked="false" clickable="false" enabled="true" focusable="false" focused="false" scrollable="false" long-clickable="false" password="false" selected="false" visible-to-user="true" bounds="[370,1088][438,1151]" drawing-order="3" hint="" display-id="0" />
                        </node>
                        <node index="3" text="" resource-id="com.linkedin.android:id/tab_notifications" class="Tab" package="com.linkedin.android" content-desc="Notifications 4 of 5" checkable="false" checked="false" clickable="true" enabled="true" focusable="true" focused="false" scrollable="false" long-clickable="true" password="false" selected="false" visible-to-user="true" bounds="[460,1088][612,1184]" drawing-order="4" hint="" display-id="0">
                          <node index="0" text="Notifications" resource-id="com.linkedin.android:id/slim_notification_badge_label" class="android.widget.TextView" package="com.linkedin.android" content-desc="" checkable="false" checked="false" clickable="false" enabled="true" focusable="false" focused="false" scrollable="false" long-clickable="false" password="false" selected="false" visible-to-user="true" bounds="[480,1148][593,1176]" drawing-order="2" hint="" display-id="0" />
                          <node index="1" text="" resource-id="com.linkedin.android:id/slim_notification_badge_icon" class="android.widget.ImageView" package="com.linkedin.android" content-desc="" checkable="false" checked="false" clickable="false" enabled="true" focusable="false" focused="false" scrollable="false" long-clickable="false" password="false" selected="false" visible-to-user="true" bounds="[512,1105][560,1153]" drawing-order="1" hint="" display-id="0" />
                          <node index="2" text="" resource-id="com.linkedin.android:id/slim_notification_coach_mark" class="android.widget.FrameLayout" package="com.linkedin.android" content-desc="" checkable="false" checked="false" clickable="false" enabled="true" focusable="false" focused="false" scrollable="false" long-clickable="false" password="false" selected="false" visible-to-user="true" bounds="[522,1088][590,1151]" drawing-order="3" hint="" display-id="0" />
                        </node>
                        <node index="4" text="" resource-id="com.linkedin.android:id/tab_jobs" class="Tab" package="com.linkedin.android" content-desc="Jobs 5 of 5" checkable="false" checked="false" clickable="true" enabled="true" focusable="true" focused="false" scrollable="false" long-clickable="true" password="false" selected="true" visible-to-user="true" bounds="[612,1088][764,1184]" drawing-order="5" hint="" display-id="0">
                          <node index="0" text="" resource-id="com.linkedin.android:id/slim_notification_badge_icon" class="android.widget.ImageView" package="com.linkedin.android" content-desc="" checkable="false" checked="false" clickable="false" enabled="true" focusable="false" focused="false" scrollable="false" long-clickable="false" password="false" selected="true" visible-to-user="true" bounds="[664,1105][712,1153]" drawing-order="1" hint="" display-id="0" />
                          <node index="1" text="Jobs" resource-id="com.linkedin.android:id/slim_notification_badge_label" class="android.widget.TextView" package="com.linkedin.android" content-desc="" checkable="false" checked="false" clickable="false" enabled="true" focusable="false" focused="false" scrollable="false" long-clickable="false" password="false" selected="true" visible-to-user="true" bounds="[667,1148][710,1176]" drawing-order="2" hint="" display-id="0" />
                          <node index="2" text="" resource-id="com.linkedin.android:id/slim_notification_coach_mark" class="android.widget.FrameLayout" package="com.linkedin.android" content-desc="" checkable="false" checked="false" clickable="false" enabled="true" focusable="false" focused="false" scrollable="false" long-clickable="false" password="false" selected="true" visible-to-user="true" bounds="[674,1088][742,1151]" drawing-order="3" hint="" display-id="0" />
                        </node>
                      </node>
                      <node index="1" text="" resource-id="com.linkedin.android:id/bottom_nav_indicator_view" class="android.view.View" package="com.linkedin.android" content-desc="" checkable="false" checked="false" clickable="false" enabled="true" focusable="false" focused="false" scrollable="false" long-clickable="false" password="false" selected="false" visible-to-user="true" bounds="[0,1088][768,1092]" drawing-order="2" hint="" display-id="0" />
                    </node>
                  </node>
                </node>
              </node>
            </node>
          </node>
        </node>
      </node>
    </node>
  </node>
</hierarchy>